cykooz.buildout.venv-1.2.1-py2.7-nspkg.pth
cykooz/buildout/venv/__init__.py
cykooz/buildout/venv/extension.py
cykooz/buildout/venv/runtests.py
cykooz/buildout/venv/tests.py
cykooz.buildout.venv-1.2.1.dist-info/METADATA
cykooz.buildout.venv-1.2.1.dist-info/WHEEL
cykooz.buildout.venv-1.2.1.dist-info/entry_points.txt
cykooz.buildout.venv-1.2.1.dist-info/namespace_packages.txt
cykooz.buildout.venv-1.2.1.dist-info/top_level.txt
cykooz.buildout.venv-1.2.1.dist-info/RECORD
