Metadata-Version: 2.1
Name: cykooz.buildout.venv
Version: 1.2.1
Summary: A zc.buildout extension for run buildout under virtual python environment.
Home-page: https://bitbucket.org/cykooz/cykooz.buildout.venv
Author: Kirill Kuzminykh
Author-email: saikuz@mail.ru
License: ZPL 2.1
Keywords: development build
Platform: UNKNOWN
Classifier: Intended Audience :: Developers
Classifier: License :: OSI Approved :: Zope Public License
Classifier: Programming Language :: Python
Classifier: Programming Language :: Python :: 2
Classifier: Programming Language :: Python :: 2.7
Classifier: Programming Language :: Python :: 3
Classifier: Programming Language :: Python :: 3.4
Classifier: Programming Language :: Python :: 3.5
Classifier: Programming Language :: Python :: 3.6
Classifier: Programming Language :: Python :: 3.7
Classifier: Framework :: Buildout
Classifier: Topic :: Software Development :: Libraries :: Python Modules
Requires-Dist: setuptools
Requires-Dist: zc.buildout
Requires-Dist: virtualenv ; python_version < "3.3"
Provides-Extra: test
Requires-Dist: pytest ; extra == 'test'
Requires-Dist: zc.buildout[test] ; extra == 'test'
